ngitl_common_py/__init__.py
ngitl_common_py/_version.py
ngitl_common_py/autostart.py
ngitl_common_py/config.py
ngitl_common_py/file_viewer_starter.py
ngitl_common_py/log.py
ngitl_common_py/py.typed
tests/__init__.py
tests/test_autostart.py
tests/test_log.py
ngitl_common_py-0.4.3.dist-info/METADATA
ngitl_common_py-0.4.3.dist-info/WHEEL
ngitl_common_py-0.4.3.dist-info/top_level.txt
ngitl_common_py-0.4.3.dist-info/RECORD
