Metadata-Version: 2.1
Name: ngitl-common-py
Version: 0.4.3
Summary: Helper classes and functions for common python problems
Home-page: https://github.com/vw-wob-it-edu-ngitl/ngitl_common_py/
Author: NG:ITL
Author-email: torsten.wylegala@volkswagen.de
License: GPLv3
Requires-Dist: pywin32 (==306)
